drfmy
