Metadata-Version: 1.0
Name: drfmy
Version: 0.0.4
Summary: dimensionality reduction
Home-page: UNKNOWN
Author: franckmy
Author-email: jsh127@163.com
License: UNKNOWN
Platform: UNKNOWN
